ai_generate.py
painter.py
server.py
game_painter-2.2.5.dist-info/METADATA
game_painter-2.2.5.dist-info/WHEEL
game_painter-2.2.5.dist-info/entry_points.txt
game_painter-2.2.5.dist-info/RECORD
