Metadata-Version: 2.4
Name: game-painter
Version: 2.2.5
Summary: 🎨 基础绘图工具 - 17个核心MCP绘图工具（含AI生图）
Author: dzqdzq
License: MIT
Keywords: AI生图,drawing,dzqdzq,graphics,mcp,painter
Classifier: Development Status :: 4 - Beta
Classifier: Intended Audience :: Developers
Classifier: License :: OSI Approved :: MIT License
Classifier: Programming Language :: Python :: 3
Classifier: Programming Language :: Python :: 3.10
Classifier: Programming Language :: Python :: 3.11
Classifier: Programming Language :: Python :: 3.12
Classifier: Programming Language :: Python :: 3.13
Classifier: Topic :: Multimedia :: Graphics
Requires-Python: >=3.10
Requires-Dist: mcp>=1.0.0
Requires-Dist: numba>=0.63.0
Requires-Dist: onnxruntime>=1.20.0
Requires-Dist: pillow>=10.0.0
Requires-Dist: rembg>=2.0.0
Requires-Dist: volcengine-python-sdk>=4.0.0
